timelimiter/__init__.py
timelimiter/counter.py
timelimiter/event_loop.py
timelimiter/exceptions.py
timelimiter/time_limiter.py
timelimiter/timeout_handler.py
timelimiter-0.1.1.dist-info/LICENSE
timelimiter-0.1.1.dist-info/METADATA
timelimiter-0.1.1.dist-info/WHEEL
timelimiter-0.1.1.dist-info/top_level.txt
timelimiter-0.1.1.dist-info/RECORD
