Metadata-Version: 2.1
Name: timelimiter
Version: 0.1.1
Summary: Python time limiter library
Author-email: Keyes Hsu <keyes.hsu@gmail.com>
License: MIT License        
Project-URL: Homepage, https://github.com/KeyesHsu/timelimiter
Project-URL: Bug Tracker, https://github.com/KeyesHsu/timelimiter/issues
Classifier: Intended Audience :: Developers
Classifier: License :: OSI Approved :: MIT License
Classifier: Operating System :: OS Independent
Classifier: Programming Language :: Python :: 3
Classifier: Programming Language :: Python :: 3.7
Classifier: Programming Language :: Python :: 3.8
Classifier: Programming Language :: Python :: 3.9
Classifier: Programming Language :: Python :: 3.10
Requires-Python: >=3.7
License-File: LICENSE
Provides-Extra: test
Requires-Dist: bumpversion ; extra == 'test'
Requires-Dist: pre-commit ; extra == 'test'
Requires-Dist: pytest ; extra == 'test'
Requires-Dist: pytest-cov ; extra == 'test'
Requires-Dist: pylint ; extra == 'test'
Requires-Dist: black ; extra == 'test'
